{
	"name": "Vimium C",
	"@time": "13/05/2022, 17:33:32",
	"time": 1652456012604,
	"environment": {
		"extension": "1.98.0",
		"platform": "linux",
		"firefox": 100
	},
	"exclusionRules": [],
	"keyMappings": [
		"#!no-check",
		"map H previousTab",
		"map L nextTab",
		"map d removeTab",
		"map D removeRightTab",
		"map u restoreTab",
		"map <c-s-h> previousTab",
		"map <c-s-l> nextTab",
		"map <a-h> goBack",
		"map <a-l> goForward",
		"map <c-d> scrollPageDown",
		"map <c-u> scrollPageUp",
		"map <a-f> LinkHints.activate dblclick",
		""
	],
	"linkHintCharacters": "asdfghjklcvnmro",
	"nextPatterns": "next,more,newer,>,›,→,»,≫,>>",
	"previousPatterns": "prev,previous,back,older,<,‹,←,«,≪,<<",
	"scrollStepSize": 220,
	"searchEngines": [
		"g|go|gg|google|Google: https://www.google.com/search?q=%s \\",
		"  www.google.com re=/^(?:\\.[a-z]{2,4})?\\/search\\b.*?[#&?]q=([^#&]*)/i\\",
		"  blank=https://www.google.com/ Google",
		"",
		"d|dd|ddg|duckduckgo: https://duckduckgo.com/?q=%s DuckDuckGo",
		"g.m|gm|g.map|gmap: https://www.google.com/maps?q=%s \\",
		"  blank=https://www.google.com/maps Google Maps",
		"",
		"y|yt: https://www.youtube.com/results?search_query=%s \\",
		"  blank=https://www.youtube.com/ YouTube",
		"",
		"w|wiki: https://www.wikipedia.org/w/index.php?search=%s Wikipedia",
		"",
		"g.s|gs|gscholar: https://scholar.google.com/scholar?q=$s \\",
		"  scholar.google.com re=/^(?:\\.[a-z]{2,4})?\\/scholar\\b.*?[#&?]q=([^#&]*)/i\\",
		"  blank=https://scholar.google.com/ Google Scholar",
		"",
		"az|amazon: https://www.amazon.com/s/?field-keywords=%s \\",
		"  blank=https://www.amazon.com/ Amazon",
		"",
		"v.m|v\\:math: vimium://math\\ $S re= Calculate",
		"",
		"gh|github: https://github.com/search?q=$s \\",
		"  blank=https://github.com/ GitHub Repo",
		"",
		"js\\:|Js: javascript:\\ $S; JavaScript",
		""
	],
	"showActionIcon": false,
	"smoothScroll": false,
	"userDefinedCss": [
		"/* #ui */",
		"/* [ Rules for the HUD and Hints go here. ] */",
		"",
		"/* link hints */",
		".LH {",
		"  border: 1px #35373e solid;",
		"  color: #295f8b;",
		"  /*box-shadow: 0px 2px 11px red;*/",
		"  border-radius: 0px;",
		"  background: unset;",
		"  margin-top: -2px;",
		"  margin-left: -2px;",
		"  z-index: 0;",
		"}",
		".LH:before {",
		"  background: #abb2bf;",
		"  position: absolute;",
		"  top: 0;",
		"  left: 0;",
		"  right: 0;",
		"  bottom: 0;",
		"  content: \"\";",
		"  z-index: -1;",
		"}",
		".D .LH {",
		"  border-color: #35373e;",
		"  color: #61afef;",
		"}",
		".D .LH:before {",
		"  background: #1e2128;",
		"}",
		"",
		"/* link hints: matching chars */",
		".MC {",
		"  color: #282c34;",
		"}",
		".D .MC {",
		"  color: #abb2bf;",
		"}",
		"",
		"/* bottom hud */",
		".HUD {",
		"  color: #282c34;",
		"  border: 2px solid #828894;",
		"  bottom: 1rem;",
		"  left: 1rem;",
		"  right: unset;",
		"  border-radius: 0px;",
		"  /*box-shadow: 0px 2px 11px red;*/",
		"  padding: 0.5rem 1rem;",
		"  height: 1.5rem !important;",
		"  line-height: unset;",
		"  /*text-transform: lowercase;*/",
		"  max-width: 420px;",
		"  min-width: unset;",
		"  line-height: 21px;",
		"  display: flex;",
		"  align-items: center;",
		"}",
		".HUD.UI {",
		"  min-width: 180px;",
		"  align-items: unset;",
		"}",
		".Omnibar {",
		"  padding-bottom: 20px;",
		"  height: 100vh !important;",
		"  width: 100vw !important;",
		"  top: 0px !important;",
		"  left: 0px !important;",
		"}",
		".HUD:after {",
		"  background: #abb2bf;",
		"  border-radius: unset;",
		"  border: none;",
		"}",
		".HUD.D {",
		"  color: #c1c7d4;",
		"  border: 1px solid #35373e;",
		"}",
		".HUD.D:after {",
		"  background: #1e2128;",
		"}",
		"",
		"/* #omni */",
		"/* [ Rules for the Vomnibar go here. ] */",
		"* {",
		"  /*font-family: \"JetBrains Mono\", monospace !important;",
		"  */",
		"}",
		".transparent {",
		"  opacity: 1;",
		"}",
		".time {",
		"}",
		".has-time {",
		"}",
		"html {",
		"  width: 100%;",
		"  height: 100%;",
		"  max-width: 90vw;",
		"  margin: auto;",
		"  background-color: #00000088;",
		"",
		"}",
		"body {",
		"  border-radius: 5px;",
		"  border: 1px solid #828894;",
		"  /*box-shadow: 0px 2px 11px red;*/",
		"  max-width: 800px;",
		"  margin: auto;",
		"  top: 10vh;",
		"}",
		"body.has-dark {",
		"  border: 1px solid #35373e;",
		"}",
		"body:after {",
		"  border: unset;",
		"}",
		"#bar {",
		"  background: rgba(247, 246, 246, 0.99);",
		"  border-bottom: 1px solid #35373e;;",
		"  height: 23px;",
		"  padding: 10px 10px 20px 20px;",
		"}",
		".has-dark #bar {",
		"  background: #1e2128;",
		"}",
		"#bar::before {",
		"  content: \"❯\";",
		"  display: inline-block;",
		"  width: 1rem;",
		"  height: 24px;",
		"  position: absolute;",
		"  left: 1rem;",
		"  z-index: 300;",
		"  padding: 4px 0;",
		"  line-height: 1.6em;",
		"  text-align: right;",
		"  color: rgba(0, 0, 0, 0.3);",
		"  font-weight: bold;",
		"}",
		".has-dark #bar::before {",
		"  color: #d4d4d4;",
		"}",
		"#input {",
		"  border: none;",
		"  background: none;",
		"  box-shadow: unset;",
		"  /* font-size: 1rem; */",
		"  color: #1f2731;",
		"  padding-left: 2rem;",
		"  max-width: 89%;",
		"  overflow-y: visible;",
		"  overflow-x: hidden;",
		"  text-overflow: ellipsis;",
		"}",
		".has-dark #input {",
		"  color: #ffffff;",
		"}",
		"#toolbar {",
		"  top: 7px;",
		"  right: 14px;",
		"}",
		"#toolbar .button {",
		"  height: 24px;",
		"  width: 24px;",
		"  padding: 5px;",
		"  cursor: pointer;",
		"  border: 3px transparent solid;",
		"  position: relative;",
		"  opacity: 0.5;",
		"  transition: 100ms ease-in-out opacity;",
		"}",
		"#toolbar .button:hover {",
		"  background: unset;",
		"  opacity: 1;",
		"}",
		"#toolbar .button > svg {",
		"  opacity: 0.5;",
		"}",
		"#toolbar .button#toggle-dark > svg {",
		"  transform: translateY(1px) rotate(45deg);",
		"}",
		"#toolbar .button#close > svg {",
		"  transform: scale(1.4);",
		"}",
		"#toolbar .button#toggle-dark .i-moon {",
		"  fill: unset;",
		"  stroke-width: 1.4;",
		"}",
		"#toolbar .button#toggle-dark .i-sun {",
		"  stroke-width: 2.1;",
		"}",
		".has-dark #toolbar .button#toggle-dark .i-moon {",
		"  fill: #e0e0e0;",
		"  stroke: #e0e0e0;",
		"}",
		".has-dark #toolbar .button#toggle-dark .i-sun {",
		"  fill: #e0e0e0;",
		"  stroke: #e0e0e0;",
		"}",
		".has-dark #toolbar .button#close > svg {",
		"  fill: #e0e0e0;",
		"  stroke: #e0e0e0;",
		"}",
		"#list {",
		"  background: rgba(247, 246, 246, 0.99);",
		"  border-radius: unset;",
		"  padding: 0px;",
		"}",
		".has-dark #list {",
		"  background: #1e2128;",
		"}",
		".item {",
		"  padding: 0px;",
		"  margin: 0px;",
		"  border: unset;",
		"  height: 46px;",
		"  padding: 10px 20px 4px 20px;",
		"  box-sizing: content-box;",
		"  cursor:pointer;",
		"}",
		".item::before {",
		"  position: absolute;",
		"  background: none;",
		"  top: 0;",
		"  left: 0;",
		"  right: 0;",
		"  bottom: 0;",
		"  content: \"\";",
		"  z-index: -1;",
		"}",
		".item.s,",
		".item:hover {",
		"  background-color: unset;",
		"",
		"}",
		".has-dark .item.s,",
		".has-dark .item:hover {",
		"",
		"}",
		".item.s::before {",
		"  background-color: rgba(255, 255, 255, 0.836);",
		"}",
		".item:hover::before {",
		"  background-color: #fff;",
		"}",
		".has-dark .item.s::before {",
		"  background-color: #17191e;",
		"  border-left: 2px #61afef solid;",
		"}",
		".item:hover::before {",
		"  border-left: 2px #61afef solid;",
		"}",
		".has-dark .item:hover::before {",
		"  background-color: #17191e;",
		"}",
		".item:hover::before {",
		"  border-left: 2px #61afef solid;",
		"}",
		".item .icon {",
		"  width: 24px;",
		"  height: 24px;",
		"  padding-right: unset;",
		"  margin-right: 10px;",
		"  margin-top: 5px;",
		"  background-position: bottom right;",
		"}",
		".has-dark .item .icon {",
		"  fill: #e0e0e0;",
		"  stroke: #e0e0e0;",
		"}",
		".item .icon path {",
		"  opacity: 0.25;",
		"  position: absolute;",
		"  z-index: -1;",
		"  transform-origin: 0px 0px;",
		"  transform: scale(0.75);",
		"}",
		".item .top {",
		"  color: #838686;",
		"  position: relative;",
		"  height: 30px;",
		"}",
		".has-dark .item .top {",
		"  color: #f1f1f1;",
		"}",
		".item .top .title {",
		"  display: inline-block;",
		"  /* font-size: 0.85rem; */",
		"  margin-top: 2px;",
		"  max-width: 70%;",
		"  overflow-y: visible;",
		"  overflow-x: hidden;",
		"  text-overflow: ellipsis;",
		"  height: 17px;",
		"}",
		".item .top .title match {",
		"  color: #363636;",
		"}",
		".has-dark .item .top .title match {",
		"  color: #61afef;",
		"  text-decoration: none;",
		"}",
		".item .top .title:empty::after {",
		"  content: \"<blank>\";",
		"}",
		".item .bottom {",
		"  margin-top: -12px;",
		"  padding-left: 14px;",
		"}",
		".item .bottom a {",
		"  color: #b6b8b8;",
		"  /* font-size: 0.6rem; */",
		"  float: left;",
		"  max-width: 70%;",
		"  overflow: hidden;",
		"  text-overflow: ellipsis;",
		"  height: 17px;",
		"}",
		".has-dark .item .bottom a {",
		"  color: #a4a4ad;",
		"}",
		".item .bottom a match {",
		"  color: #686c6d;",
		"}",
		".has-dark .item .bottom a match {",
		"  color: #b1b9c2;",
		"}",
		".history {",
		"  d: path(\"M8 10.8A32 32 0 1 1 0 32h6a26 26 1 1 0 6.25-17L20 23H0V3zM28 18v21l15 8 4-5-13-7V18\");",
		"}",
		"",
		"/* #find */",
		"/* [ Rules for the FindBar (inside the iframe) go here. ] */",
		"* {",
		"  /*font-family: \"JetBrains Mono\", monospace !important;*/",
		"}",
		":host,",
		"body {",
		"  background-color: unset !important;",
		"  margin: 0 !important;",
		"  padding: 0 !important;",
		"}",
		":host(.D),",
		"body.D {",
		"  background-color: unset !important;",
		"}",
		".r {",
		"  color: #838686;",
		"  border: none;",
		"  border-radius: unset;",
		"  box-shadow: unset;",
		"  background: unset;",
		"  height: 10px;",
		"}",
		".r.D {",
		"  background: unset;",
		"  color: #d4d4d4;",
		"}",
		"#i {",
		"  color: #1f2731;",
		"}",
		".D #i {",
		"  color: #ffffff;",
		"}",
		"",
		"/* #find:host */",
		"/* [ Rules _for web pages while only enabled when there's a FindMode_ go here. ] */",
		"::selection {",
		"  color: black !important;",
		"  background-color: #e06c75 !important;",
		"}",
		"",
		"/* #find:selection */",
		"/* [ When Vimium C executes find and there's at least one match, this can be used to change styles of the selection area ] */",
		"::selection {",
		"  color: black !important;",
		"  background-color: #e5c07b !important;",
		"}",
		""
	],
	"vimSync": true,
	"vomnibarOptions": {
		"maxMatches": 10,
		"queryInterval": 333,
		"sizes": "77,3,44,0.8",
		"styles": "time",
		"actions": ""
	}
}